mcp_test/__init__.py
mcp_test/local_mcp.py
mcp_test_example-0.0.1.dist-info/licenses/LICENSE
mcp_test_example-0.0.1.dist-info/METADATA
mcp_test_example-0.0.1.dist-info/WHEEL
mcp_test_example-0.0.1.dist-info/top_level.txt
mcp_test_example-0.0.1.dist-info/RECORD
