Metadata-Version: 2.4
Name: mcp-test-example
Version: 0.0.1
Summary: MCP test example
Home-page: https://github.com/pypa/sampleproject
Author: jamie_test
Author-email: 1820510720@qq.com
Classifier: Programming Language :: Python :: 3
Classifier: License :: OSI Approved :: MIT License
Classifier: Operating System :: OS Independent
Requires-Python: >=3.12
License-File: LICENSE
Dynamic: author
Dynamic: author-email
Dynamic: classifier
Dynamic: description
Dynamic: description-content-type
Dynamic: home-page
Dynamic: license-file
Dynamic: requires-python
Dynamic: summary
